{ "compressionlevel":-1,
 "height":9,
 "infinite":false,
 "layers":[
        {
         "draworder":"topdown",
         "id":9,
         "name":"wheat",
         "objects":[],
         "opacity":1,
         "type":"objectgroup",
         "visible":true,
         "x":0,
         "y":0
        }, 
        {
         "draworder":"topdown",
         "id":8,
         "name":"environment",
         "objects":[
                {
                 "gid":54,
                 "height":32,
                 "id":116,
                 "name":"",
                 "properties":[
                        {
                         "name":"frame_cols",
                         "type":"int",
                         "value":1
                        }, 
                        {
                         "name":"frame_rows",
                         "type":"int",
                         "value":1
                        }, 
                        {
                         "name":"name",
                         "type":"string",
                         "value":"fence3"
                        }],
                 "rotation":0,
                 "type":"Decoration",
                 "visible":true,
                 "width":32,
                 "x":0,
                 "y":64
                }, 
                {
                 "gid":54,
                 "height":32,
                 "id":117,
                 "name":"",
                 "properties":[
                        {
                         "name":"frame_cols",
                         "type":"int",
                         "value":1
                        }, 
                        {
                         "name":"frame_rows",
                         "type":"int",
                         "value":1
                        }, 
                        {
                         "name":"name",
                         "type":"string",
                         "value":"fence3"
                        }],
                 "rotation":0,
                 "type":"Decoration",
                 "visible":true,
                 "width":32,
                 "x":0,
                 "y":96
                }, 
                {
                 "gid":54,
                 "height":32,
                 "id":118,
                 "name":"",
                 "properties":[
                        {
                         "name":"frame_cols",
                         "type":"int",
                         "value":1
                        }, 
                        {
                         "name":"frame_rows",
                         "type":"int",
                         "value":1
                        }, 
                        {
                         "name":"name",
                         "type":"string",
                         "value":"fence3"
                        }],
                 "rotation":0,
                 "type":"Decoration",
                 "visible":true,
                 "width":32,
                 "x":0,
                 "y":128
                }, 
                {
                 "gid":54,
                 "height":32,
                 "id":119,
                 "name":"",
                 "properties":[
                        {
                         "name":"frame_cols",
                         "type":"int",
                         "value":1
                        }, 
                        {
                         "name":"frame_rows",
                         "type":"int",
                         "value":1
                        }, 
                        {
                         "name":"name",
                         "type":"string",
                         "value":"fence3"
                        }],
                 "rotation":0,
                 "type":"Decoration",
                 "visible":true,
                 "width":32,
                 "x":0,
                 "y":160
                }, 
                {
                 "gid":54,
                 "height":32,
                 "id":120,
                 "name":"",
                 "properties":[
                        {
                         "name":"frame_cols",
                         "type":"int",
                         "value":1
                        }, 
                        {
                         "name":"frame_rows",
                         "type":"int",
                         "value":1
                        }, 
                        {
                         "name":"name",
                         "type":"string",
                         "value":"fence3"
                        }],
                 "rotation":0,
                 "type":"Decoration",
                 "visible":true,
                 "width":32,
                 "x":0,
                 "y":192
                }, 
                {
                 "gid":54,
                 "height":32,
                 "id":121,
                 "name":"",
                 "properties":[
                        {
                         "name":"frame_cols",
                         "type":"int",
                         "value":1
                        }, 
                        {
                         "name":"frame_rows",
                         "type":"int",
                         "value":1
                        }, 
                        {
                         "name":"name",
                         "type":"string",
                         "value":"fence3"
                        }],
                 "rotation":0,
                 "type":"Decoration",
                 "visible":true,
                 "width":32,
                 "x":0,
                 "y":224
                }, 
                {
                 "gid":54,
                 "height":32,
                 "id":122,
                 "name":"",
                 "properties":[
                        {
                         "name":"frame_cols",
                         "type":"int",
                         "value":1
                        }, 
                        {
                         "name":"frame_rows",
                         "type":"int",
                         "value":1
                        }, 
                        {
                         "name":"name",
                         "type":"string",
                         "value":"fence3"
                        }],
                 "rotation":0,
                 "type":"Decoration",
                 "visible":true,
                 "width":32,
                 "x":0,
                 "y":256
                }, 
                {
                 "gid":54,
                 "height":32,
                 "id":123,
                 "name":"",
                 "properties":[
                        {
                         "name":"frame_cols",
                         "type":"int",
                         "value":1
                        }, 
                        {
                         "name":"frame_rows",
                         "type":"int",
                         "value":1
                        }, 
                        {
                         "name":"name",
                         "type":"string",
                         "value":"fence3"
                        }],
                 "rotation":0,
                 "type":"Decoration",
                 "visible":true,
                 "width":32,
                 "x":0,
                 "y":288
                }, 
                {
                 "height":288,
                 "id":124,
                 "name":"",
                 "rotation":0,
                 "type":"EnvCollidable",
                 "visible":true,
                 "width":20.6601,
                 "x":0,
                 "y":0
                }, 
                {
                 "gid":53,
                 "height":32,
                 "id":125,
                 "name":"",
                 "properties":[
                        {
                         "name":"frame_cols",
                         "type":"int",
                         "value":1
                        }, 
                        {
                         "name":"frame_rows",
                         "type":"int",
                         "value":1
                        }, 
                        {
                         "name":"name",
                         "type":"string",
                         "value":"fence5"
                        }],
                 "rotation":0,
                 "type":"Decoration",
                 "visible":true,
                 "width":32,
                 "x":480,
                 "y":64
                }, 
                {
                 "gid":53,
                 "height":32,
                 "id":126,
                 "name":"",
                 "properties":[
                        {
                         "name":"frame_cols",
                         "type":"int",
                         "value":1
                        }, 
                        {
                         "name":"frame_rows",
                         "type":"int",
                         "value":1
                        }, 
                        {
                         "name":"name",
                         "type":"string",
                         "value":"fence5"
                        }],
                 "rotation":0,
                 "type":"Decoration",
                 "visible":true,
                 "width":32,
                 "x":480,
                 "y":96
                }, 
                {
                 "gid":53,
                 "height":32,
                 "id":127,
                 "name":"",
                 "properties":[
                        {
                         "name":"frame_cols",
                         "type":"int",
                         "value":1
                        }, 
                        {
                         "name":"frame_rows",
                         "type":"int",
                         "value":1
                        }, 
                        {
                         "name":"name",
                         "type":"string",
                         "value":"fence5"
                        }],
                 "rotation":0,
                 "type":"Decoration",
                 "visible":true,
                 "width":32,
                 "x":480,
                 "y":128
                }, 
                {
                 "gid":53,
                 "height":32,
                 "id":128,
                 "name":"",
                 "properties":[
                        {
                         "name":"frame_cols",
                         "type":"int",
                         "value":1
                        }, 
                        {
                         "name":"frame_rows",
                         "type":"int",
                         "value":1
                        }, 
                        {
                         "name":"name",
                         "type":"string",
                         "value":"fence5"
                        }],
                 "rotation":0,
                 "type":"Decoration",
                 "visible":true,
                 "width":32,
                 "x":480,
                 "y":160
                }, 
                {
                 "gid":53,
                 "height":32,
                 "id":129,
                 "name":"",
                 "properties":[
                        {
                         "name":"frame_cols",
                         "type":"int",
                         "value":1
                        }, 
                        {
                         "name":"frame_rows",
                         "type":"int",
                         "value":1
                        }, 
                        {
                         "name":"name",
                         "type":"string",
                         "value":"fence5"
                        }],
                 "rotation":0,
                 "type":"Decoration",
                 "visible":true,
                 "width":32,
                 "x":480,
                 "y":224
                }, 
                {
                 "gid":53,
                 "height":32,
                 "id":130,
                 "name":"",
                 "properties":[
                        {
                         "name":"frame_cols",
                         "type":"int",
                         "value":1
                        }, 
                        {
                         "name":"frame_rows",
                         "type":"int",
                         "value":1
                        }, 
                        {
                         "name":"name",
                         "type":"string",
                         "value":"fence5"
                        }],
                 "rotation":0,
                 "type":"Decoration",
                 "visible":true,
                 "width":32,
                 "x":480,
                 "y":192
                }, 
                {
                 "gid":53,
                 "height":32,
                 "id":131,
                 "name":"",
                 "properties":[
                        {
                         "name":"frame_cols",
                         "type":"int",
                         "value":1
                        }, 
                        {
                         "name":"frame_rows",
                         "type":"int",
                         "value":1
                        }, 
                        {
                         "name":"name",
                         "type":"string",
                         "value":"fence5"
                        }],
                 "rotation":0,
                 "type":"Decoration",
                 "visible":true,
                 "width":32,
                 "x":480,
                 "y":256
                },
            
                {
                 "gid":53,
                 "height":32,
                 "id":132,
                 "name":"",
                 "properties":[
                        {
                         "name":"frame_cols",
                         "type":"int",
                         "value":1
                        }, 
                        {
                         "name":"frame_rows",
                         "type":"int",
                         "value":1
                        }, 
                        {
                         "name":"name",
                         "type":"string",
                         "value":"fence5"
                        }],
                 "rotation":0,
                 "type":"Decoration",
                 "visible":true,
                 "width":32,
                 "x":480,
                 "y":288
                }, 
                {
                 "height":288,
                 "id":133,
                 "name":"",
                 "rotation":0,
                 "type":"EnvCollidable",
                 "visible":true,
                 "width":19.8564,
                 "x":492.144,
                 "y":0
                }, 
                {
                 "gid":54,
                 "height":32,
                 "id":134,
                 "name":"",
                 "properties":[
                        {
                         "name":"frame_cols",
                         "type":"int",
                         "value":1
                        }, 
                        {
                         "name":"frame_rows",
                         "type":"int",
                         "value":1
                        }, 
                        {
                         "name":"name",
                         "type":"string",
                         "value":"fence3"
                        }],
                 "rotation":0,
                 "type":"Decoration",
                 "visible":true,
                 "width":32,
                 "x":0,
                 "y":32
                }, 
                {
                 "gid":53,
                 "height":32,
                 "id":135,
                 "name":"",
                 "properties":[
                        {
                         "name":"frame_cols",
                         "type":"int",
                         "value":1
                        }, 
                        {
                         "name":"frame_rows",
                         "type":"int",
                         "value":1
                        }, 
                        {
                         "name":"name",
                         "type":"string",
                         "value":"fence5"
                        }],
                 "rotation":0,
                 "type":"Decoration",
                 "visible":true,
                 "width":32,
                 "x":480,
                 "y":32
                }, 
                {
                 "gid":44,
                 "height":32,
                 "id":136,
                 "name":"",
                 "rotation":0,
                 "type":"Rock",
                 "visible":true,
                 "width":32,
                 "x":224,
                 "y":192
                }],
         "opacity":1,
         "type":"objectgroup",
         "visible":true,
         "x":0,
         "y":0
        }, 
        {
         "draworder":"topdown",
         "id":7,
         "name":"entities",
         "objects":[],
         "opacity":1,
         "type":"objectgroup",
         "visible":true,
         "x":0,
         "y":0
        }],
 "nextlayerid":11,
 "nextobjectid":137,
 "orientation":"orthogonal",
 "properties":[
        {
         "name":"map-type",
         "propertytype":"MapType",
         "type":"string",
         "value":"middle-middle"
        }],
 "renderorder":"right-down",
 "tiledversion":"1.10.2",
 "tileheight":32,
 "tilesets":[
        {
         "firstgid":1,
         "source":"entities.tsx"
        }, 
        {
         "firstgid":4,
         "source":"maps.tsx"
        }, 
        {
         "firstgid":43,
         "source":"environment.tsx"
        }],
 "tilewidth":32,
 "type":"map",
 "version":"1.10",
 "width":16
}