{ "compressionlevel":-1,
 "height":9,
 "infinite":false,
 "layers":[
        {
         "draworder":"topdown",
         "id":9,
         "name":"wheat",
         "objects":[
                {
                 "gid":25,
                 "height":288,
                 "id":158,
                 "name":"",
                 "properties":[
                        {
                         "name":"blade_color_scale",
                         "type":"float",
                         "value":10
                        }, 
                        {
                         "name":"name",
                         "type":"string",
                         "value":"unit_tr_2"
                        }],
                 "rotation":0,
                 "type":"Map",
                 "visible":true,
                 "width":512,
                 "x":0,
                 "y":288
                }],
         "opacity":1,
         "type":"objectgroup",
         "visible":true,
         "x":0,
         "y":0
        }, 
        {
         "draworder":"topdown",
         "id":8,
         "name":"environment",
         "objects":[
                {
                 "gid":35,
                 "height":64,
                 "id":138,
                 "name":"",
                 "rotation":0,
                 "type":"PlantingSpot",
                 "visible":true,
                 "width":96,
                 "x":378,
                 "y":277
                }, 
                {
                 "gid":48,
                 "height":32,
                 "id":160,
                 "name":"",
                 "properties":[
                        {
                         "name":"frame_cols",
                         "type":"int",
                         "value":1
                        }, 
                        {
                         "name":"frame_rows",
                         "type":"int",
                         "value":1
                        }, 
                        {
                         "name":"name",
                         "type":"string",
                         "value":"fence1"
                        }],
                 "rotation":0,
                 "type":"Decoration",
                 "visible":true,
                 "width":32,
                 "x":32,
                 "y":32
                }, 
                {
                 "gid":48,
                 "height":32,
                 "id":161,
                 "name":"",
                 "properties":[
                        {
                         "name":"frame_cols",
                         "type":"int",
                         "value":1
                        }, 
                        {
                         "name":"frame_rows",
                         "type":"int",
                         "value":1
                        }, 
                        {
                         "name":"name",
                         "type":"string",
                         "value":"fence1"
                        }],
                 "rotation":0,
                 "type":"Decoration",
                 "visible":true,
                 "width":32,
                 "x":64,
                 "y":32
                }, 
                {
                 "gid":48,
                 "height":32,
                 "id":162,
                 "name":"",
                 "properties":[
                        {
                         "name":"frame_cols",
                         "type":"int",
                         "value":1
                        }, 
                        {
                         "name":"frame_rows",
                         "type":"int",
                         "value":1
                        }, 
                        {
                         "name":"name",
                         "type":"string",
                         "value":"fence1"
                        }],
                 "rotation":0,
                 "type":"Decoration",
                 "visible":true,
                 "width":32,
                 "x":96,
                 "y":32
                }, 
                {
                 "gid":48,
                 "height":32,
                 "id":163,
                 "name":"",
                 "properties":[
                        {
                         "name":"frame_cols",
                         "type":"int",
                         "value":1
                        }, 
                        {
                         "name":"frame_rows",
                         "type":"int",
                         "value":1
                        }, 
                        {
                         "name":"name",
                         "type":"string",
                         "value":"fence1"
                        }],
                 "rotation":0,
                 "type":"Decoration",
                 "visible":true,
                 "width":32,
                 "x":128,
                 "y":32
                }, 
                {
                 "gid":48,
                 "height":32,
                 "id":164,
                 "name":"",
                 "properties":[
                        {
                         "name":"frame_cols",
                         "type":"int",
                         "value":1
                        }, 
                        {
                         "name":"frame_rows",
                         "type":"int",
                         "value":1
                        }, 
                        {
                         "name":"name",
                         "type":"string",
                         "value":"fence1"
                        }],
                 "rotation":0,
                 "type":"Decoration",
                 "visible":true,
                 "width":32,
                 "x":160,
                 "y":32
                }, 
                {
                 "gid":48,
                 "height":32,
                 "id":165,
                 "name":"",
                 "properties":[
                        {
                         "name":"frame_cols",
                         "type":"int",
                         "value":1
                        }, 
                        {
                         "name":"frame_rows",
                         "type":"int",
                         "value":1
                        }, 
                        {
                         "name":"name",
                         "type":"string",
                         "value":"fence1"
                        }],
                 "rotation":0,
                 "type":"Decoration",
                 "visible":true,
                 "width":32,
                 "x":192,
                 "y":32
                }, 
                {
                 "gid":48,
                 "height":32,
                 "id":166,
                 "name":"",
                 "properties":[
                        {
                         "name":"frame_cols",
                         "type":"int",
                         "value":1
                        }, 
                        {
                         "name":"frame_rows",
                         "type":"int",
                         "value":1
                        }, 
                        {
                         "name":"name",
                         "type":"string",
                         "value":"fence1"
                        }],
                 "rotation":0,
                 "type":"Decoration",
                 "visible":true,
                 "width":32,
                 "x":224,
                 "y":32
                }, 
                {
                 "gid":48,
                 "height":32,
                 "id":167,
                 "name":"",
                 "properties":[
                        {
                         "name":"frame_cols",
                         "type":"int",
                         "value":1
                        }, 
                        {
                         "name":"frame_rows",
                         "type":"int",
                         "value":1
                        }, 
                        {
                         "name":"name",
                         "type":"string",
                         "value":"fence1"
                        }],
                 "rotation":0,
                 "type":"Decoration",
                 "visible":true,
                 "width":32,
                 "x":256,
                 "y":32
                }, 
                {
                 "gid":48,
                 "height":32,
                 "id":168,
                 "name":"",
                 "properties":[
                        {
                         "name":"frame_cols",
                         "type":"int",
                         "value":1
                        }, 
                        {
                         "name":"frame_rows",
                         "type":"int",
                         "value":1
                        }, 
                        {
                         "name":"name",
                         "type":"string",
                         "value":"fence1"
                        }],
                 "rotation":0,
                 "type":"Decoration",
                 "visible":true,
                 "width":32,
                 "x":288,
                 "y":32
                }, 
                {
                 "gid":48,
                 "height":32,
                 "id":169,
                 "name":"",
                 "properties":[
                        {
                         "name":"frame_cols",
                         "type":"int",
                         "value":1
                        }, 
                        {
                         "name":"frame_rows",
                         "type":"int",
                         "value":1
                        }, 
                        {
                         "name":"name",
                         "type":"string",
                         "value":"fence1"
                        }],
                 "rotation":0,
                 "type":"Decoration",
                 "visible":true,
                 "width":32,
                 "x":320,
                 "y":32
                }, 
                {
                 "gid":48,
                 "height":32,
                 "id":170,
                 "name":"",
                 "properties":[
                        {
                         "name":"frame_cols",
                         "type":"int",
                         "value":1
                        }, 
                        {
                         "name":"frame_rows",
                         "type":"int",
                         "value":1
                        }, 
                        {
                         "name":"name",
                         "type":"string",
                         "value":"fence1"
                        }],
                 "rotation":0,
                 "type":"Decoration",
                 "visible":true,
                 "width":32,
                 "x":352,
                 "y":32
                }, 
                {
                 "gid":48,
                 "height":32,
                 "id":171,
                 "name":"",
                 "properties":[
                        {
                         "name":"frame_cols",
                         "type":"int",
                         "value":1
                        }, 
                        {
                         "name":"frame_rows",
                         "type":"int",
                         "value":1
                        }, 
                        {
                         "name":"name",
                         "type":"string",
                         "value":"fence1"
                        }],
                 "rotation":0,
                 "type":"Decoration",
                 "visible":true,
                 "width":32,
                 "x":384,
                 "y":32
                }, 
                {
                 "gid":48,
                 "height":32,
                 "id":172,
                 "name":"",
                 "properties":[
                        {
                         "name":"frame_cols",
                         "type":"int",
                         "value":1
                        }, 
                        {
                         "name":"frame_rows",
                         "type":"int",
                         "value":1
                        }, 
                        {
                         "name":"name",
                         "type":"string",
                         "value":"fence1"
                        }],
                 "rotation":0,
                 "type":"Decoration",
                 "visible":true,
                 "width":32,
                 "x":416,
                 "y":32
                }, 
                {
                 "gid":48,
                 "height":32,
                 "id":173,
                 "name":"",
                 "properties":[
                        {
                         "name":"frame_cols",
                         "type":"int",
                         "value":1
                        }, 
                        {
                         "name":"frame_rows",
                         "type":"int",
                         "value":1
                        }, 
                        {
                         "name":"name",
                         "type":"string",
                         "value":"fence1"
                        }],
                 "rotation":0,
                 "type":"Decoration",
                 "visible":true,
                 "width":32,
                 "x":448,
                 "y":32
                }, 
                {
                 "height":15.6439,
                 "id":174,
                 "name":"",
                 "rotation":0,
                 "type":"EnvCollidable",
                 "visible":true,
                 "width":512,
                 "x":0,
                 "y":12
                },
            
                {
                 "gid":48,
                 "height":32,
                 "id":175,
                 "name":"",
                 "properties":[
                        {
                         "name":"frame_cols",
                         "type":"int",
                         "value":1
                        }, 
                        {
                         "name":"frame_rows",
                         "type":"int",
                         "value":1
                        }, 
                        {
                         "name":"name",
                         "type":"string",
                         "value":"fence1"
                        }],
                 "rotation":0,
                 "type":"Decoration",
                 "visible":true,
                 "width":32,
                 "x":0,
                 "y":32
                }, 
                {
                 "gid":47,
                 "height":32,
                 "id":176,
                 "name":"",
                 "properties":[
                        {
                         "name":"frame_cols",
                         "type":"int",
                         "value":1
                        }, 
                        {
                         "name":"frame_rows",
                         "type":"int",
                         "value":1
                        }, 
                        {
                         "name":"name",
                         "type":"string",
                         "value":"fence2"
                        }],
                 "rotation":0,
                 "type":"Decoration",
                 "visible":true,
                 "width":32,
                 "x":480,
                 "y":32
                }, 
                {
                 "gid":45,
                 "height":32,
                 "id":177,
                 "name":"",
                 "properties":[
                        {
                         "name":"frame_cols",
                         "type":"int",
                         "value":1
                        }, 
                        {
                         "name":"frame_rows",
                         "type":"int",
                         "value":1
                        }, 
                        {
                         "name":"name",
                         "type":"string",
                         "value":"fence5"
                        }],
                 "rotation":0,
                 "type":"Decoration",
                 "visible":true,
                 "width":32,
                 "x":480,
                 "y":64
                }, 
                {
                 "gid":45,
                 "height":32,
                 "id":178,
                 "name":"",
                 "properties":[
                        {
                         "name":"frame_cols",
                         "type":"int",
                         "value":1
                        }, 
                        {
                         "name":"frame_rows",
                         "type":"int",
                         "value":1
                        }, 
                        {
                         "name":"name",
                         "type":"string",
                         "value":"fence5"
                        }],
                 "rotation":0,
                 "type":"Decoration",
                 "visible":true,
                 "width":32,
                 "x":480,
                 "y":96
                }, 
                {
                 "gid":45,
                 "height":32,
                 "id":179,
                 "name":"",
                 "properties":[
                        {
                         "name":"frame_cols",
                         "type":"int",
                         "value":1
                        }, 
                        {
                         "name":"frame_rows",
                         "type":"int",
                         "value":1
                        }, 
                        {
                         "name":"name",
                         "type":"string",
                         "value":"fence5"
                        }],
                 "rotation":0,
                 "type":"Decoration",
                 "visible":true,
                 "width":32,
                 "x":480,
                 "y":128
                }, 
                {
                 "gid":45,
                 "height":32,
                 "id":180,
                 "name":"",
                 "properties":[
                        {
                         "name":"frame_cols",
                         "type":"int",
                         "value":1
                        }, 
                        {
                         "name":"frame_rows",
                         "type":"int",
                         "value":1
                        }, 
                        {
                         "name":"name",
                         "type":"string",
                         "value":"fence5"
                        }],
                 "rotation":0,
                 "type":"Decoration",
                 "visible":true,
                 "width":32,
                 "x":480,
                 "y":160
                }, 
                {
                 "gid":45,
                 "height":32,
                 "id":181,
                 "name":"",
                 "properties":[
                        {
                         "name":"frame_cols",
                         "type":"int",
                         "value":1
                        }, 
                        {
                         "name":"frame_rows",
                         "type":"int",
                         "value":1
                        }, 
                        {
                         "name":"name",
                         "type":"string",
                         "value":"fence5"
                        }],
                 "rotation":0,
                 "type":"Decoration",
                 "visible":true,
                 "width":32,
                 "x":480,
                 "y":224
                }, 
                {
                 "gid":45,
                 "height":32,
                 "id":182,
                 "name":"",
                 "properties":[
                        {
                         "name":"frame_cols",
                         "type":"int",
                         "value":1
                        }, 
                        {
                         "name":"frame_rows",
                         "type":"int",
                         "value":1
                        }, 
                        {
                         "name":"name",
                         "type":"string",
                         "value":"fence5"
                        }],
                 "rotation":0,
                 "type":"Decoration",
                 "visible":true,
                 "width":32,
                 "x":480,
                 "y":192
                }, 
                {
                 "gid":45,
                 "height":32,
                 "id":183,
                 "name":"",
                 "properties":[
                        {
                         "name":"frame_cols",
                         "type":"int",
                         "value":1
                        }, 
                        {
                         "name":"frame_rows",
                         "type":"int",
                         "value":1
                        }, 
                        {
                         "name":"name",
                         "type":"string",
                         "value":"fence5"
                        }],
                 "rotation":0,
                 "type":"Decoration",
                 "visible":true,
                 "width":32,
                 "x":480,
                 "y":256
                }, 
                {
                 "gid":45,
                 "height":32,
                 "id":184,
                 "name":"",
                 "properties":[
                        {
                         "name":"frame_cols",
                         "type":"int",
                         "value":1
                        }, 
                        {
                         "name":"frame_rows",
                         "type":"int",
                         "value":1
                        }, 
                        {
                         "name":"name",
                         "type":"string",
                         "value":"fence5"
                        }],
                 "rotation":0,
                 "type":"Decoration",
                 "visible":true,
                 "width":32,
                 "x":480,
                 "y":288
                }, 
                {
                 "height":288,
                 "id":185,
                 "name":"",
                 "rotation":0,
                 "type":"EnvCollidable",
                 "visible":true,
                 "width":19.8564,
                 "x":492.144,
                 "y":0
                }, 
                {
                 "gid":45,
                 "height":32,
                 "id":186,
                 "name":"",
                 "properties":[
                        {
                         "name":"frame_cols",
                         "type":"int",
                         "value":1
                        }, 
                        {
                         "name":"frame_rows",
                         "type":"int",
                         "value":1
                        }, 
                        {
                         "name":"name",
                         "type":"string",
                         "value":"fence5"
                        }],
                 "rotation":0,
                 "type":"Decoration",
                 "visible":true,
                 "width":32,
                 "x":96,
                 "y":106
                }, 
                {
                 "gid":45,
                 "height":32,
                 "id":187,
                 "name":"",
                 "properties":[
                        {
                         "name":"frame_cols",
                         "type":"int",
                         "value":1
                        }, 
                        {
                         "name":"frame_rows",
                         "type":"int",
                         "value":1
                        }, 
                        {
                         "name":"name",
                         "type":"string",
                         "value":"fence5"
                        }],
                 "rotation":0,
                 "type":"Decoration",
                 "visible":true,
                 "width":32,
                 "x":96,
                 "y":170
                }, 
                {
                 "gid":45,
                 "height":32,
                 "id":188,
                 "name":"",
                 "properties":[
                        {
                         "name":"frame_cols",
                         "type":"int",
                         "value":1
                        }, 
                        {
                         "name":"frame_rows",
                         "type":"int",
                         "value":1
                        }, 
                        {
                         "name":"name",
                         "type":"string",
                         "value":"fence5"
                        }],
                 "rotation":0,
                 "type":"Decoration",
                 "visible":true,
                 "width":32,
                 "x":96,
                 "y":138
                }, 
                {
                 "gid":45,
                 "height":32,
                 "id":189,
                 "name":"",
                 "properties":[
                        {
                         "name":"frame_cols",
                         "type":"int",
                         "value":1
                        }, 
                        {
                         "name":"frame_rows",
                         "type":"int",
                         "value":1
                        }, 
                        {
                         "name":"name",
                         "type":"string",
                         "value":"fence5"
                        }],
                 "rotation":0,
                 "type":"Decoration",
                 "visible":true,
                 "width":32,
                 "x":96,
                 "y":202
                }, 
                {
                 "gid":45,
                 "height":32,
                 "id":190,
                 "name":"",
                 "properties":[
                        {
                         "name":"frame_cols",
                         "type":"int",
                         "value":1
                        }, 
                        {
                         "name":"frame_rows",
                         "type":"int",
                         "value":1
                        }, 
                        {
                         "name":"name",
                         "type":"string",
                         "value":"fence5"
                        }],
                 "rotation":0,
                 "type":"Decoration",
                 "visible":true,
                 "width":32,
                 "x":96,
                 "y":234
                },
            
                {
                 "gid":42,
                 "height":32,
                 "id":191,
                 "name":"",
                 "properties":[
                        {
                         "name":"frame_cols",
                         "type":"int",
                         "value":1
                        }, 
                        {
                         "name":"frame_rows",
                         "type":"int",
                         "value":1
                        }, 
                        {
                         "name":"name",
                         "type":"string",
                         "value":"fence8"
                        }],
                 "rotation":0,
                 "type":"Decoration",
                 "visible":true,
                 "width":32,
                 "x":96,
                 "y":266
                }, 
                {
                 "gid":43,
                 "height":32,
                 "id":192,
                 "name":"",
                 "properties":[
                        {
                         "name":"frame_cols",
                         "type":"int",
                         "value":1
                        }, 
                        {
                         "name":"frame_rows",
                         "type":"int",
                         "value":1
                        }, 
                        {
                         "name":"name",
                         "type":"string",
                         "value":"fence7"
                        }],
                 "rotation":0,
                 "type":"Decoration",
                 "visible":true,
                 "width":32,
                 "x":64,
                 "y":266
                }, 
                {
                 "gid":43,
                 "height":32,
                 "id":193,
                 "name":"",
                 "properties":[
                        {
                         "name":"frame_cols",
                         "type":"int",
                         "value":1
                        }, 
                        {
                         "name":"frame_rows",
                         "type":"int",
                         "value":1
                        }, 
                        {
                         "name":"name",
                         "type":"string",
                         "value":"fence7"
                        }],
                 "rotation":0,
                 "type":"Decoration",
                 "visible":true,
                 "width":32,
                 "x":32,
                 "y":266
                }, 
                {
                 "gid":43,
                 "height":32,
                 "id":194,
                 "name":"",
                 "properties":[
                        {
                         "name":"frame_cols",
                         "type":"int",
                         "value":1
                        }, 
                        {
                         "name":"frame_rows",
                         "type":"int",
                         "value":1
                        }, 
                        {
                         "name":"name",
                         "type":"string",
                         "value":"fence7"
                        }],
                 "rotation":0,
                 "type":"Decoration",
                 "visible":true,
                 "width":32,
                 "x":0,
                 "y":266
                }, 
                {
                 "height":12.388,
                 "id":195,
                 "name":"",
                 "rotation":0,
                 "type":"EnvCollidable",
                 "visible":true,
                 "width":118,
                 "x":2,
                 "y":251.612
                }, 
                {
                 "height":175.119,
                 "id":196,
                 "name":"",
                 "rotation":0,
                 "type":"EnvCollidable",
                 "visible":true,
                 "width":12.037,
                 "x":107.963,
                 "y":88.881
                }],
         "opacity":1,
         "type":"objectgroup",
         "visible":true,
         "x":0,
         "y":0
        }, 
        {
         "draworder":"topdown",
         "id":7,
         "name":"entities",
         "objects":[
                {
                 "gid":2,
                 "height":32,
                 "id":106,
                 "name":"",
                 "rotation":0,
                 "type":"Carrot",
                 "visible":true,
                 "width":32,
                 "x":32,
                 "y":192
                }, 
                {
                 "gid":1,
                 "height":32,
                 "id":107,
                 "name":"",
                 "rotation":0,
                 "type":"Farmer",
                 "visible":true,
                 "width":32,
                 "x":384,
                 "y":192
                }, 
                {
                 "gid":3,
                 "height":32,
                 "id":113,
                 "name":"",
                 "rotation":0,
                 "type":"Baby",
                 "visible":true,
                 "width":32,
                 "x":448,
                 "y":224
                }, 
                {
                 "gid":3,
                 "height":32,
                 "id":119,
                 "name":"",
                 "rotation":0,
                 "type":"Baby",
                 "visible":true,
                 "width":32,
                 "x":384,
                 "y":96
                }, 
                {
                 "gid":3,
                 "height":32,
                 "id":122,
                 "name":"",
                 "rotation":0,
                 "type":"Baby",
                 "visible":true,
                 "width":32,
                 "x":160,
                 "y":256
                }, 
                {
                 "gid":3,
                 "height":32,
                 "id":159,
                 "name":"",
                 "rotation":0,
                 "type":"Baby",
                 "visible":true,
                 "width":32,
                 "x":224,
                 "y":288
                }, 
                {
                 "gid":3,
                 "height":32,
                 "id":144,
                 "name":"",
                 "rotation":0,
                 "type":"Baby",
                 "visible":true,
                 "width":32,
                 "x":192,
                 "y":96
                }, 
                {
                 "gid":3,
                 "height":32,
                 "id":148,
                 "name":"",
                 "rotation":0,
                 "type":"Baby",
                 "visible":true,
                 "width":32,
                 "x":64,
                 "y":96
                }, 
                {
                 "gid":3,
                 "height":32,
                 "id":123,
                 "name":"",
                 "rotation":0,
                 "type":"Baby",
                 "visible":true,
                 "width":32,
                 "x":416,
                 "y":160
                }, 
                {
                 "gid":3,
                 "height":32,
                 "id":141,
                 "name":"",
                 "rotation":0,
                 "type":"Baby",
                 "visible":true,
                 "width":32,
                 "x":0,
                 "y":224
                }, 
                {
                 "gid":3,
                 "height":32,
                 "id":152,
                 "name":"",
                 "rotation":0,
                 "type":"Baby",
                 "visible":true,
                 "width":32,
                 "x":0,
                 "y":96
                }, 
                {
                 "gid":3,
                 "height":32,
                 "id":142,
                 "name":"",
                 "rotation":0,
                 "type":"Baby",
                 "visible":true,
                 "width":32,
                 "x":192,
                 "y":192
                }, 
                {
                 "gid":3,
                 "height":32,
                 "id":147,
                 "name":"",
                 "rotation":0,
                 "type":"Baby",
                 "visible":true,
                 "width":32,
                 "x":32,
                 "y":128
                }, 
                {
                 "gid":3,
                 "height":32,
                 "id":128,
                 "name":"",
                 "rotation":0,
                 "type":"Baby",
                 "visible":true,
                 "width":32,
                 "x":288,
                 "y":96
                }, 
                {
                 "gid":3,
                 "height":32,
                 "id":145,
                 "name":"",
                 "rotation":0,
                 "type":"Baby",
                 "visible":true,
                 "width":32,
                 "x":256,
                 "y":64
                }, 
                {
                 "gid":3,
                 "height":32,
                 "id":150,
                 "name":"",
                 "rotation":0,
                 "type":"Baby",
                 "visible":true,
                 "width":32,
                 "x":320,
                 "y":256
                },
            
                {
                 "gid":3,
                 "height":32,
                 "id":130,
                 "name":"",
                 "rotation":0,
                 "type":"Baby",
                 "visible":true,
                 "width":32,
                 "x":288,
                 "y":192
                }, 
                {
                 "gid":3,
                 "height":32,
                 "id":149,
                 "name":"",
                 "rotation":0,
                 "type":"Baby",
                 "visible":true,
                 "width":32,
                 "x":224,
                 "y":128
                }, 
                {
                 "gid":3,
                 "height":32,
                 "id":133,
                 "name":"",
                 "rotation":0,
                 "type":"Baby",
                 "visible":true,
                 "width":32,
                 "x":352,
                 "y":128
                }],
         "opacity":1,
         "type":"objectgroup",
         "visible":true,
         "x":0,
         "y":0
        }],
 "nextlayerid":11,
 "nextobjectid":197,
 "orientation":"orthogonal",
 "properties":[
        {
         "name":"map-type",
         "propertytype":"MapType",
         "type":"string",
         "value":"middle-middle"
        }],
 "renderorder":"right-down",
 "tiledversion":"1.10.2",
 "tileheight":32,
 "tilesets":[
        {
         "firstgid":1,
         "source":"entities.tsx"
        }, 
        {
         "firstgid":4,
         "source":"maps.tsx"
        }, 
        {
         "firstgid":35,
         "source":"environment.tsx"
        }],
 "tilewidth":32,
 "type":"map",
 "version":"1.10",
 "width":16
}